Metadata-Version: 2.1
Name: indic-nlp-library-IT2
Version: 0.0.1
Summary: The goal of the Indic NLP Library is to build Python based libraries for common text processing and Natural Language Processing in Indian languages. This fork is specialized for IndicTrans2.
Home-page: https://github.com/VarunGumma/indic_nlp_library
Author: Varun Gumma, Anoop Kunchukuttan
Author-email: varun230999@gmail.com
License: MIT
Classifier: Programming Language :: Python :: 3
Classifier: License :: OSI Approved :: MIT License
Classifier: Operating System :: OS Independent
Requires-Python: >=3.8
License-File: LICENSE
Requires-Dist: sphinx-argparse
Requires-Dist: sphinx-rtd-theme
Requires-Dist: morfessor
Requires-Dist: pandas
Requires-Dist: numpy
